snippets/__init__.py
snippets/decorators.py
snippets/evaluate.py
snippets/logs.py
snippets/mixin.py
snippets/perf.py
snippets/utils.py
python_snippets-0.1.3.dist-info/METADATA
python_snippets-0.1.3.dist-info/WHEEL
python_snippets-0.1.3.dist-info/RECORD
